menu/__init__.py
menu/plugin.py
pytest_menu-0.0.4.dist-info/DESCRIPTION.rst
pytest_menu-0.0.4.dist-info/METADATA
pytest_menu-0.0.4.dist-info/RECORD
pytest_menu-0.0.4.dist-info/WHEEL
pytest_menu-0.0.4.dist-info/entry_points.txt
pytest_menu-0.0.4.dist-info/metadata.json
pytest_menu-0.0.4.dist-info/top_level.txt
