Metadata-Version: 2.0
Name: pytest-menu
Version: 0.0.4
Summary: A pytest plugin for console based interactive test selection just after the collection phase
Home-page: https://github.com/nyantec/pytest-menu
Author: Karl Engelhardt
Author-email: ken@nyantec.com
License: MIT
Download-URL: https://github.com/nyantec/pytest-menu/tarball/0.0.4
Platform: linux
Classifier: Development Status :: 3 - Alpha
Classifier: Intended Audience :: Developers
Classifier: Topic :: Software Development :: Testing
Classifier: Programming Language :: Python :: 3
Classifier: Environment :: Console
Requires-Dist: npyscreen (>=4.0)
Requires-Dist: pytest (>=2.4.2)
